{
  "hash": "9c03010988321765",
  "paragraph": "Ridgewood's single-family market is firing on all cylinders. Eighty-eight sales over six months at a median of $1,462,500 tells you there is real volume here, and the numbers back up what that volume means. Sellers are dictating terms, with 76 percent of homes selling above asking and a sale-to-list ratio of 1.12. Median days on market sits at 10.5 days, which means priced homes are moving fast and multiple offer situations are routine. The range is wide, from $620,000 to $4,750,000, so Ridgewood accommodates buyers across the spectrum, but the median floor is solid and the market confidence is unmistakable. Multi-family properties, though sparse at only five sales, show similar strength with 80 percent selling above list and a median of $1,280,000. If you're selling, this is a seller's market. If you're buying, you're competing, and pricing strategically matters more than waiting for the perfect home to appear on the market.",
  "fallback": false,
  "reason": null,
  "retried": true,
  "firstDraft": "Ridgewood's single-family market is firing on all cylinders. Eighty-eight sales over six months at a median of $1,462,500 tells you there is real volume here, and the numbers back up what that volume means. Sellers are dictating terms, with 76 percent of homes selling above asking and a sale-to-list ratio of 1.12. Median days on market sits at just 10.5 days, which means priced homes are moving fast and multiple offer situations are routine. The range is wide, from $620,000 to $4,750,000, so Ridgewood accommodates buyers across the spectrum, but the median floor is solid and the market confidence is unmistakable. Multi-family properties, though sparse at only five sales, show similar strength with 80 percent selling above list and a median of $1,280,000. If you're selling, this is a seller's market. If you're buying, you're competing, and pricing strategically matters more than waiting for the perfect home to appear on the market.",
  "usage": {
    "input_tokens": 3855,
    "cache_creation_input_tokens": 0,
    "cache_read_input_tokens": 0,
    "cache_creation": {
      "ephemeral_5m_input_tokens": 0,
      "ephemeral_1h_input_tokens": 0
    },
    "output_tokens": 237,
    "service_tier": "standard",
    "inference_geo": "not_available"
  },
  "generatedAt": "2026-07-19T15:27:12.453Z"
}